odoo/addons/sale_order_invoicing_picking_filter_grouping_criteria/README.rst
odoo/addons/sale_order_invoicing_picking_filter_grouping_criteria/__init__.py
odoo/addons/sale_order_invoicing_picking_filter_grouping_criteria/__manifest__.py
odoo/addons/sale_order_invoicing_picking_filter_grouping_criteria/readme/CONFIGURE.md
odoo/addons/sale_order_invoicing_picking_filter_grouping_criteria/readme/CONTRIBUTORS.md
odoo/addons/sale_order_invoicing_picking_filter_grouping_criteria/readme/DESCRIPTION.md
odoo/addons/sale_order_invoicing_picking_filter_grouping_criteria/readme/ROADMAP.md
odoo/addons/sale_order_invoicing_picking_filter_grouping_criteria/readme/USAGE.md
odoo/addons/sale_order_invoicing_picking_filter_grouping_criteria/static/description/icon.png
odoo/addons/sale_order_invoicing_picking_filter_grouping_criteria/static/description/index.html
odoo/addons/sale_order_invoicing_picking_filter_grouping_criteria/tests/__init__.py
odoo/addons/sale_order_invoicing_picking_filter_grouping_criteria/tests/test_sale_invoicing.py
odoo/addons/sale_order_invoicing_picking_filter_grouping_criteria/wizards/__init__.py
odoo/addons/sale_order_invoicing_picking_filter_grouping_criteria/wizards/sale_advance_payment_inv.py
odoo_addon_sale_order_invoicing_picking_filter_grouping_criteria-16.0.1.1.0.dist-info/METADATA
odoo_addon_sale_order_invoicing_picking_filter_grouping_criteria-16.0.1.1.0.dist-info/WHEEL
odoo_addon_sale_order_invoicing_picking_filter_grouping_criteria-16.0.1.1.0.dist-info/top_level.txt
odoo_addon_sale_order_invoicing_picking_filter_grouping_criteria-16.0.1.1.0.dist-info/RECORD
