Metadata-Version: 2.1
Name: odoo-addon-sale_order_invoicing_picking_filter_grouping_criteria
Version: 16.0.1.1.0
Summary: Glues the picking filter with sale_order_invoicing_grouping_criteria
Home-page: https://github.com/sygel-technology/sy-sale-workflow
Author: Sygel, Odoo Community Association (OCA)
Author-email: support@odoo-community.org
License: AGPL-3
Classifier: Programming Language :: Python
Classifier: Framework :: Odoo
Classifier: Framework :: Odoo :: 16.0
Classifier: License :: OSI Approved :: GNU Affero General Public License v3
Requires-Python: >=3.10
Requires-Dist: odoo-addon-sale-order-invoicing-grouping-criteria<16.1dev,>=16.0dev
Requires-Dist: odoo-addon-sale-order-invoicing-picking-filter<16.1dev,>=16.0dev
Requires-Dist: odoo<16.1dev,>=16.0a
